tuneable_counterfactuals_explainer/__init__.py
tuneable_counterfactuals_explainer/explainer.py
tuneable_counterfactuals_explainer/scorer.py
tuneable_counterfactuals_explainer/searcher.py
tuneable_counterfactuals_explainer/single_variable_explainer.py
tuneable_counterfactuals_explainer-0.0.7.dist-info/METADATA
tuneable_counterfactuals_explainer-0.0.7.dist-info/WHEEL
tuneable_counterfactuals_explainer-0.0.7.dist-info/licenses/LICENCE
tuneable_counterfactuals_explainer-0.0.7.dist-info/RECORD
