Metadata-Version: 2.3
Name: tuneable_counterfactuals_explainer
Version: 0.0.7
Summary: A python package for generating counterfactual explanations for machine learning models
Project-URL: Homepage, https://github.com/JoshanParmar/TuneableCounterfactuals
Project-URL: Issues, https://github.com/JoshanParmar/TuneableCounterfactuals/issues
License-File: LICENCE
Classifier: Operating System :: OS Independent
Classifier: Programming Language :: Python :: 3
Requires-Python: >=3.8
Requires-Dist: matplotlib>=3.8.0
Requires-Dist: numpy>=1.26.1
Requires-Dist: pandas>=2.1.2
Requires-Dist: scikit-learn>=1.3.2
Requires-Dist: tqdm>=4.66.4
